LICENSE
MANIFEST.in
README.rst
setup.py
example_module/__init__.py
example_module/models.py
example_module/nexus_modules.py
example_project/__init__.py
example_project/manage.py
example_project/settings.py
example_project/urls.py
new_nexus.egg-info/PKG-INFO
new_nexus.egg-info/SOURCES.txt
new_nexus.egg-info/dependency_links.txt
new_nexus.egg-info/not-zip-safe
new_nexus.egg-info/requires.txt
new_nexus.egg-info/top_level.txt
nexus/__init__.py
nexus/conf.py
nexus/models.py
nexus/modules.py
nexus/nexus_modules.py
nexus/sites.py
nexus/media/css/admin.css
nexus/media/css/facebox.css
nexus/media/css/nexus.css
nexus/media/img/breadcrumb.png
nexus/media/img/loading.gif
nexus/media/img/nexus_logo.png
nexus/media/img/admin/icon_add.gif
nexus/media/img/admin/icon_change.gif
nexus/media/img/admin/icon_delete.gif
nexus/media/img/admin/nav-bg.gif
nexus/media/img/facebox/closelabel.png
nexus/media/img/facebox/loading.gif
nexus/media/js/nexus.js
nexus/media/js/lib/jquery.js
nexus/media/js/lib/jquery.tmpl.js
nexus/media/js/lib/facebox/facebox.js
nexus/templates/nexus/base.html
nexus/templates/nexus/dashboard.html
nexus/templates/nexus/login.html
nexus/templates/nexus/module.html
nexus/templates/nexus/navigation.html
nexus/templates/nexus/admin/app_index.html
nexus/templates/nexus/admin/base.html
nexus/templates/nexus/admin/base_site.html
nexus/templates/nexus/admin/change_form.html
nexus/templates/nexus/admin/change_list.html
nexus/templates/nexus/admin/delete_confirmation.html
nexus/templates/nexus/admin/delete_selected_confirmation.html
nexus/templates/nexus/admin/index.html
nexus/templates/nexus/admin/object_history.html
nexus/templates/nexus/admin/password_change_done.html
nexus/templates/nexus/admin/password_change_form.html
nexus/templates/nexus/admin/submit_line.html
nexus/templates/nexus/admin/dashboard/index.html
nexus/templatetags/__init__.py
nexus/templatetags/nexus_admin.py
nexus/templatetags/nexus_helpers.py