Metadata-Version: 1.1
Name: new-nexus
Version: 0.3.1
Summary: An extendable admin interface
Home-page: http://github.com/disqus/nexus
Author: Disqus
Author-email: opensource@disqus.com
License: UNKNOWN
Platform: UNKNOWN
Classifier: Framework :: Django
Classifier: Intended Audience :: Developers
Classifier: Intended Audience :: System Administrators
Classifier: Operating System :: OS Independent
Classifier: Topic :: Software Development
